{
  "indexes": [
    {
      "collectionGroup": "recipes",
      "queryScope": "COLLECTION",
      "fields": [
        { "fieldPath": "userId", "order": "ASCENDING" },
        { "fieldPath": "createdAt", "order": "DESCENDING" }
      ]
    },
    {
      "collectionGroup": "recipes",
      "queryScope": "COLLECTION",
      "fields": [
        { "fieldPath": "userId", "order": "ASCENDING" },
        { "fieldPath": "derivedFrom", "order": "ASCENDING" }
      ]
    },
    {
      "collectionGroup": "recipe-versions",
      "queryScope": "COLLECTION",
      "fields": [
        { "fieldPath": "recipeId", "order": "ASCENDING" },
        { "fieldPath": "number", "order": "ASCENDING" }
      ]
    },
    {
      "collectionGroup": "trials",
      "queryScope": "COLLECTION",
      "fields": [
        { "fieldPath": "userId", "order": "ASCENDING" },
        { "fieldPath": "recipeId", "order": "ASCENDING" },
        { "fieldPath": "executedAt", "order": "DESCENDING" }
      ]
    },
    {
      "collectionGroup": "trials",
      "queryScope": "COLLECTION",
      "fields": [
        { "fieldPath": "userId", "order": "ASCENDING" },
        { "fieldPath": "executedAt", "order": "DESCENDING" }
      ]
    },
    {
      "collectionGroup": "proposals",
      "queryScope": "COLLECTION",
      "fields": [
        { "fieldPath": "userId", "order": "ASCENDING" },
        { "fieldPath": "recipeId", "order": "ASCENDING" }
      ]
    }
  ],
  "fieldOverrides": []
}
